[{"img_url_number": "2328959", "content_article_url": "https://hanime1.me/comic/79326", "content_article_name": "[城爪草(crazy clover club )] 衛宮家佚事 (chinese)"}, {"img_url_number": "2294238", "content_article_url": "https://hanime1.me/comic/77395", "content_article_name": "[pixiv](kusayarou) shirou emiya tsf [chinese] [aelitr个人汉化]"}, {"img_url_number": "2223349", "content_article_url": "https://hanime1.me/comic/73747", "content_article_name": "(c70) [keumaya (inoue junichi)] hyena 2   walpurgis no yoru 2 (fate stay night) [chinese] [牛肝菌汉化]"}, {"img_url_number": "2221267", "content_article_url": "https://hanime1.me/comic/73700", "content_article_name": "(c67) [keumaya (inoue junichi)] walpurgisnacht / walpurgis no yoru (fate/stay night) [chinese] [牛肝菌汉化]"}, {"img_url_number": "2176667", "content_article_url": "https://hanime1.me/comic/71703", "content_article_name": "[snowrich (iida toyoyuki)] second semester ii (fate/stay night) [chinese] [digital]"}, {"img_url_number": "2167856", "content_article_url": "https://hanime1.me/comic/70831", "content_article_name": "(c95) [high thrust (inomaru)] rinkan mahou -soushuuhen- (fate/stay night) [chinese] [b·c漢化]"}, {"img_url_number": "2158513", "content_article_url": "https://hanime1.me/comic/71218", "content_article_name": "[crazy clover club (kuroha nue)] emiya shirou no nichijou (fate/stay night) [chinese] [路人漢化]"}, {"img_url_number": "2148207", "content_article_url": "https://hanime1.me/comic/70454", "content_article_name": "(c95) [high thrust (inomaru)] rinkan mahou -soushuuhen- (fate/stay night) [chinese] [b·c漢化]"}, {"img_url_number": "2123320", "content_article_url": "https://hanime1.me/comic/69447", "content_article_name": "(c94) [nawairo sonata (himitsu)] tenkuu to meikai no ori (fate/grand order) [chinese] [azukino1个人重嵌] [decensored]"}, {"img_url_number": "1971971", "content_article_url": "https://hanime1.me/comic/729", "content_article_name": "[z.a.p. (zucchini)] avenger? (fate/grand order) [chinese] [黎欧x新桥月白日语社汉化]"}, {"img_url_number": "1914279", "content_article_url": "https://hanime1.me/comic/3263", "content_article_name": "(dai 2-kai rainbow festa) [crazy clover club (kuroha nue)] emiya shirou no isshuukan (fate/stay night) [chinese] [九十九鏡真你媽難刷漢化]"}, {"img_url_number": "1887643", "content_article_url": "https://hanime1.me/comic/4983", "content_article_name": "(c95) [strawberry milk studio (lunaluku)] shikkin mahou shoujo 3 (fate/kaleid liner prisma illya) [chinese] [saw汉化组]"}, {"img_url_number": "1843289", "content_article_url": "https://hanime1.me/comic/7568", "content_article_name": "[kyockchokyock (kyockcho)] tohsaka shimai ryoujoku (fate/stay night) [chinese] [胸垫汉化组] [digital]"}, {"img_url_number": "1839129", "content_article_url": "https://hanime1.me/comic/7804", "content_article_name": "[rubbish selecting squad (namonashi)] re31 (fate/stay night) [chinese] [無邪気漢化組]"}, {"img_url_number": "1838535", "content_article_url": "https://hanime1.me/comic/7837", "content_article_name": "[rubbish selecting squad (namonashi)] re31 (fate/stay night) [chinese] [無邪気漢化組]"}, {"img_url_number": "1813271", "content_article_url": "https://hanime1.me/comic/9103", "content_article_name": "[kyockchokyock (kyockcho)] tohsaka shimai ryoujoku (fate/stay night) [chinese] [無邪気漢化組] [digital]"}, {"img_url_number": "1748485", "content_article_url": "https://hanime1.me/comic/12372", "content_article_name": "(c96) [abarenbow tengu (izumi yuujiro)] kotori 16 (fate/stay night) [chinese] [皮蛋蛋个人汉化]"}, {"img_url_number": "1677327", "content_article_url": "https://hanime1.me/comic/16356", "content_article_name": "[merkonig] b-trayal 6 (fate/stay night) [chinese] [流木个人汉化]"}, {"img_url_number": "1664727", "content_article_url": "https://hanime1.me/comic/17005", "content_article_name": "[rubbish selecting squad (namonashi)] re30 (fate/stay night) [chinese] [無邪気漢化組]"}, {"img_url_number": "1661703", "content_article_url": "https://hanime1.me/comic/17118", "content_article_name": "(c96) [kikei yuugatou (kurai nao)] rinrinkankan -β- (fate/stay night) [chinese] [新桥月白日语社]"}, {"img_url_number": "1629866", "content_article_url": "https://hanime1.me/comic/18796", "content_article_name": "[kyockchokyock (kyockcho)] tohsaka shimai ryoujoku -rin hen- (fate/stay night) [chinese] [無邪気漢化組] [digital]"}, {"img_url_number": "1629370", "content_article_url": "https://hanime1.me/comic/18827", "content_article_name": "[kyockchokyock (kyockcho)] tohsaka shimai ryoujoku -rin hen- (fate/stay night) [chinese] [silver.m个人汉化] [digital]"}, {"img_url_number": "1570141", "content_article_url": "https://hanime1.me/comic/22037", "content_article_name": "(c97) [kodoku intelligence (nanao)] the book of sakura 4 (fate/stay night) [chinese] [兔司姬漢化組]"}, {"img_url_number": "1549897", "content_article_url": "https://hanime1.me/comic/23340", "content_article_name": "[nyuu koubou (nyuu)] oidemase!! 2-jigen fuuzoku gakuen | 歓迎光臨!!2次元風俗學園 (various) [chinese] [digital]"}, {"img_url_number": "1545619", "content_article_url": "https://hanime1.me/comic/23620", "content_article_name": "(c97) [chural-an (naturalton)] fgo no ashibon 8 | fgo的足控本8 (fate/grand order) [chinese] [谜之汉化组x·alter]"}, {"img_url_number": "1470585", "content_article_url": "https://hanime1.me/comic/26969", "content_article_name": "(c88) [tokkan magasashi musume (asahi)] nee-san, watashi zutto anata no koto daikirai deshita (fate/stay night) [chinese] [洛鳶漢化組]"}, {"img_url_number": "1441482", "content_article_url": "https://hanime1.me/comic/28827", "content_article_name": "[nawairo sonata (himitsu)] tenkuu to meikai no ori (fate/grand order) [chinese]"}, {"img_url_number": "1415265", "content_article_url": "https://hanime1.me/comic/29981", "content_article_name": "(comic1☆2) [h.b (b-river)] red degeneration -day/3- (fate/stay night) [chinese] [不咕鸟汉化组]"}, {"img_url_number": "1413802", "content_article_url": "https://hanime1.me/comic/30042", "content_article_name": "(c75) [h.b (b-river)] red degeneration -day/4- (fate/stay night) [chinese] [不咕鸟汉化组]"}, {"img_url_number": "1364033", "content_article_url": "https://hanime1.me/comic/32138", "content_article_name": "(c94) [high thrust (inomaru)] rinkan mahou 4 (fate/stay night) [chinese] [不咕鸟汉化组]"}, {"img_url_number": "1359388", "content_article_url": "https://hanime1.me/comic/32327", "content_article_name": "(super26) [ambi75 (yuyama chika)] futari, hajimete no xxx (fate/stay night) [chinese] [無邪気漢化組]"}, {"img_url_number": "1358755", "content_article_url": "https://hanime1.me/comic/32354", "content_article_name": "(super26) [ambi75 (yuyama chika)] futari, hajimete no xxx (fate/stay night) [chinese] [無邪気漢化組]"}, {"img_url_number": "1330645", "content_article_url": "https://hanime1.me/comic/33586", "content_article_name": "(c93) [abarenbow tengu (izumi yuujiro)] kotori 15 (fate/stay night) [chinese] [不咕鸟汉化组]"}, {"img_url_number": "1330600", "content_article_url": "https://hanime1.me/comic/33587", "content_article_name": "(c93) [abarenbow tengu (izumi yuujiro)] kotori 15 (fate/stay night) [chinese] [盲鸡汉化组]"}, {"img_url_number": "1302217", "content_article_url": "https://hanime1.me/comic/34870", "content_article_name": "[bakuretsu fusen (denkichi)] fate/delusions of grandeur (fate/hollow ataraxia) [chinese]"}, {"img_url_number": "1280692", "content_article_url": "https://hanime1.me/comic/35868", "content_article_name": "(c94) [ruiketsuan (namidame)] emiya ke futei koukou ryouiki ～tosaka rin no baai～ (fate/stay night) [chinese] [無邪気漢化組]"}, {"img_url_number": "1268816", "content_article_url": "https://hanime1.me/comic/36541", "content_article_name": " type‐moon 10th anniversary phantasm - sensha otoko [chinese] [打酱油个人汉化]"}, {"img_url_number": "1261563", "content_article_url": "https://hanime1.me/comic/36924", "content_article_name": "[bakuretsu fusen (denkichi)] fate/delusions of grandeur (fate/hollow ataraxia) [chinese] [incomplete]"}, {"img_url_number": "1253815", "content_article_url": "https://hanime1.me/comic/37198", "content_article_name": "[bakuretsu fusen (denkichi)] fate/delusions of grandeur (fate/hollow ataraxia) [chinese] [incomplete]"}, {"img_url_number": "1233243", "content_article_url": "https://hanime1.me/comic/38075", "content_article_name": "(c88) [high thrust (inomaru)] rinkan mahou 2 boost (fate/stay night) [chinese] [很惠的惠惠漢化]"}, {"img_url_number": "1204224", "content_article_url": "https://hanime1.me/comic/39528", "content_article_name": "[73feti (hinoe nami)] kanojo to aiken (fate/stay night)  [chinese]"}, {"img_url_number": "1164321", "content_article_url": "https://hanime1.me/comic/41597", "content_article_name": "(c93) [furuike (sumiya)] kokoro wa karada de dekiteiru 2 (fate/grand order) [chinese] [m-no-tamashii×無邪気漢化組]"}, {"img_url_number": "1146890", "content_article_url": "https://hanime1.me/comic/42405", "content_article_name": "(super25) [monica (azuma)] midnight waltz (fate/stay night) [chinese]"}, {"img_url_number": "1145107", "content_article_url": "https://hanime1.me/comic/42487", "content_article_name": "[overdose (hashiba yachi)] jyunketsu ruby wa tengai no shita de (fate/stay night) [chinese] [digital]"}, {"img_url_number": "1130654", "content_article_url": "https://hanime1.me/comic/43161", "content_article_name": "(c92) [moonphase (yuran)] moon phase material 2 (fate/grand order) [chinese] [無邪気漢化組]"}, {"img_url_number": "1121701", "content_article_url": "https://hanime1.me/comic/43500", "content_article_name": "[atugi de 5 (murlachrot)] zettai majuu rinkan (fate/grand order) [chinese] [ce家族社] [digital]"}, {"img_url_number": "1113160", "content_article_url": "https://hanime1.me/comic/43866", "content_article_name": " [tamaranchi (sinbo tamaran)] euphoria ii ~mahou tsukai no yoru~ + alliance (mahou tsukai no yoru, fate/stay night) [chinese] [逆襲漢化] "}, {"img_url_number": "1111844", "content_article_url": "https://hanime1.me/comic/43908", "content_article_name": "(spark11) [un-moto shoko (un-moto)] masaka ano tosaka-san ga jugyouchuu ni (fate/stay night) [chinese]"}, {"img_url_number": "1108865", "content_article_url": "https://hanime1.me/comic/44048", "content_article_name": "(c92) [furuike (sumiya)] kokoro wa karada de dekiteiru (fate/grand order) [chinese] [無邪気漢化組]"}, {"img_url_number": "1107625", "content_article_url": "https://hanime1.me/comic/44107", "content_article_name": "(c92) [hokkebain! (halcon)] chaldea shiko shiko material vol. 1 (fate/grand order) [chinese] [无毒汉化组]"}, {"img_url_number": "1105907", "content_article_url": "https://hanime1.me/comic/44197", "content_article_name": "(c92) [mtsp (jin)] tosaka-ke no kakei jijou 10 (fate/stay night) [chinese] [脸肿汉化组]"}, {"img_url_number": "1105297", "content_article_url": "https://hanime1.me/comic/44237", "content_article_name": "(c92) [z.a.p. (zucchini)] shirou-kun harem!! mizugi de yuuwaku shichau zo hen (fate/stay night) [chinese] [塔布里斯個人漢化]"}, {"img_url_number": "1104726", "content_article_url": "https://hanime1.me/comic/44262", "content_article_name": "(c92) [mtsp (jin)] tosaka-ke no kakei jijou 10 (fate/stay night) [chinese] [無邪気漢化組]"}, {"img_url_number": "1102855", "content_article_url": "https://hanime1.me/comic/44394", "content_article_name": "(c92) [moonphase (yuran)] moon phase material 2 (fate/grand order) [chinese] [無邪気漢化組]"}, {"img_url_number": "1088409", "content_article_url": "https://hanime1.me/comic/45295", "content_article_name": "(super25) [monica (azuma)] red x red (fate/stay night) [chinese]"}, {"img_url_number": "1050099", "content_article_url": "https://hanime1.me/comic/47149", "content_article_name": "(sc24) [takeda syouten (takeda sora)] question-7 (fate/stay night) [chinese]"}, {"img_url_number": "1048523", "content_article_url": "https://hanime1.me/comic/47194", "content_article_name": "[mushoku shijidou (kuda)] iyi (fate/stay night) [chinese] [digital]"}, {"img_url_number": "1046269", "content_article_url": "https://hanime1.me/comic/47275", "content_article_name": "(c71) [taiyaki yaketa (ikeda shuuko)] hajimari no yoru ni (fate/stay night) [chinese]"}, {"img_url_number": "1044262", "content_article_url": "https://hanime1.me/comic/47371", "content_article_name": " [tamaranchi (sinbo tamaran)] euphoria ii ~mahou tsukai no yoru~ + alliance (mahou tsukai no yoru, fate/stay night) [chinese] [逆襲漢化] "}, {"img_url_number": "1044016", "content_article_url": "https://hanime1.me/comic/47382", "content_article_name": " [tamaranchi (sinbo tamaran)] euphoria ii ~mahou tsukai no yoru~ + alliance (mahou tsukai no yoru, fate/stay night) [chinese] [逆襲漢化] "}, {"img_url_number": "1042454", "content_article_url": "https://hanime1.me/comic/47414", "content_article_name": "(sc23) [shibakko. (shibasaki ako)] relation (fate/stay night) [chinese]"}, {"img_url_number": "1041486", "content_article_url": "https://hanime1.me/comic/47448", "content_article_name": "(sc24) [ryu-seki-do (nagare hyo-go)] lachesis (fate/stay night) [chinese]"}, {"img_url_number": "1041033", "content_article_url": "https://hanime1.me/comic/47458", "content_article_name": "(c71) [einfach, c.s. (tomoya, himemiya aya)] ar a commemorative book of winter (fate/stay night) [chinese]"}, {"img_url_number": "1040415", "content_article_url": "https://hanime1.me/comic/47480", "content_article_name": "(西協fff) 恐怖編外伝af fate 原作 (chinese)"}, {"img_url_number": "1039360", "content_article_url": "https://hanime1.me/comic/47508", "content_article_name": "(c91) [high thrust (inomaru)] rinkan mahou 3 (fate/stay night) [chinese] [mega巨莖怪漢化]"}, {"img_url_number": "1037716", "content_article_url": "https://hanime1.me/comic/47565", "content_article_name": "(c69) [katou seiki seisakusho (katou402)] fate gakuen alternative (fate/stay night) [chinese] [322漢化]"}, {"img_url_number": "1028432", "content_article_url": "https://hanime1.me/comic/48013", "content_article_name": "(c76) [yami ni ugomeku (dokurosan)] smells like rin tohsaka (fate/stay night) [chinese] [臭鼬娘漢化組]"}, {"img_url_number": "1027110", "content_article_url": "https://hanime1.me/comic/48056", "content_article_name": "(c76) [yami ni ugomeku (dokurosan)] smells like rin tohsaka (fate/stay night) [chinese] [臭鼬娘漢化組]"}, {"img_url_number": "1012514", "content_article_url": "https://hanime1.me/comic/48827", "content_article_name": "(c91) [chural-an (naturalton)] fgo no ashibon 3 (fate/grand order) [chinese] [性趣之门x无毒汉化组]"}, {"img_url_number": "1010771", "content_article_url": "https://hanime1.me/comic/48927", "content_article_name": "(ccosaka104) [secret scarlet (takamura emi)] herb tea wa ikaga? (fate/stay night) [chinese]"}, {"img_url_number": "1006138", "content_article_url": "https://hanime1.me/comic/49123", "content_article_name": "[shinpakusu teika (usami rui)] majestic (fate/stay night) [chinese]"}, {"img_url_number": "998299", "content_article_url": "https://hanime1.me/comic/49470", "content_article_name": "(mimiket 10) [last eden (amane mari)] infinite emotion (fate/stay night) [chinese]"}, {"img_url_number": "996984", "content_article_url": "https://hanime1.me/comic/49520", "content_article_name": "(c69) [pocky club (akiba miya)] time limit (fate/hollow ataraxia) [chinese]"}, {"img_url_number": "996756", "content_article_url": "https://hanime1.me/comic/49528", "content_article_name": "(c73) [gemou the cat (yukako)] fakers (fate/stay night) [chinese]"}, {"img_url_number": "996707", "content_article_url": "https://hanime1.me/comic/49530", "content_article_name": "[ahemaru (henrik)] rin no inran funtouki (kouhen) (fate/stay night) [chinese] [罗洁爱儿个人汉化]"}, {"img_url_number": "996705", "content_article_url": "https://hanime1.me/comic/49531", "content_article_name": "[ahemaru (henrik)] rin no inran funtouki (zenpen) (fate/stay night) [chinese] [罗洁爱儿个人汉化]"}, {"img_url_number": "996035", "content_article_url": "https://hanime1.me/comic/49566", "content_article_name": "(c72) [favorites (yorarry)] gensou ichiya (fate/stay night) [chinese]"}, {"img_url_number": "994221", "content_article_url": "https://hanime1.me/comic/49658", "content_article_name": "(c76) [mumu@ (shirokai mua)] dekkaku nacchatta! (fate/stay night) [chinese]"}, {"img_url_number": "992083", "content_article_url": "https://hanime1.me/comic/49747", "content_article_name": "(c89) [snowrich (iida toyoyuki)] have a tea break (fate/stay night) [chinese]"}, {"img_url_number": "991808", "content_article_url": "https://hanime1.me/comic/49758", "content_article_name": "[yukako] rakugaki manga (fate/stay night) [chinese]"}, {"img_url_number": "986919", "content_article_url": "https://hanime1.me/comic/49996", "content_article_name": "(c72) [nitakaya (ichifuji nitaka)] auto und adler (fate/stay night) [chinese]"}, {"img_url_number": "983225", "content_article_url": "https://hanime1.me/comic/50170", "content_article_name": "[yukako] rakugaki manga (fate/stay night) [chinese]"}, {"img_url_number": "981818", "content_article_url": "https://hanime1.me/comic/50242", "content_article_name": "(c70) [einfach (tomoya)] kyuurinbon. the thing which remains (fate/stay night) [chinese]"}, {"img_url_number": "973412", "content_article_url": "https://hanime1.me/comic/50734", "content_article_name": "(c82) [nonsense (em)] blue eclipse (fate/stay night) [chinese]"}, {"img_url_number": "970950", "content_article_url": "https://hanime1.me/comic/50854", "content_article_name": "[yukako] rakugaki manga (fate/stay night) [chinese]"}, {"img_url_number": "742583", "content_article_url": "https://hanime1.me/comic/50892", "content_article_name": "(c90) [abarenbow tengu (izumi yuujiro)] kotori 13 (fate/stay night) [chinese] [屏幕髒了漢化組]"}, {"img_url_number": "969137", "content_article_url": "https://hanime1.me/comic/50937", "content_article_name": "(cr35) [koubai gekka (kouno mizuho)] secret window (fate/stay night) [chinese]"}, {"img_url_number": "969131", "content_article_url": "https://hanime1.me/comic/50938", "content_article_name": "(cr36) [teikokudou (asakura karen)] yume de, yume nara. (fate/stay night) [chinese]"}, {"img_url_number": "968074", "content_article_url": "https://hanime1.me/comic/50996", "content_article_name": "(c77) [mtsp (jin)] tohsaka-ke no kakei jijou 6 (fate/stay night) [chinese] [yang個人漢化]"}, {"img_url_number": "968072", "content_article_url": "https://hanime1.me/comic/50997", "content_article_name": "(c88) [mtsp (jin)] tohsaka-ke no kakei jijou 2 (tosaka-ke no kakei jijou soushuuhen 1) (fate/stay night) [chinese] [yang個人漢化]"}, {"img_url_number": "968071", "content_article_url": "https://hanime1.me/comic/50999", "content_article_name": "(c88) [mtsp (jin)] tohsaka-ke no kakei jijou 1 (tosaka-ke no kakei jijou soushuuhen 1) (fate/stay night) [chinese] [yang個人漢化]"}, {"img_url_number": "966735", "content_article_url": "https://hanime1.me/comic/51072", "content_article_name": "(super22) [1000+10 (atsuyu, douiukotonano)] rin-chan ga futanari ni natte archer to ecchi suru hon (fate/stay night) [chinese]"}, {"img_url_number": "965965", "content_article_url": "https://hanime1.me/comic/51124", "content_article_name": "(c69) [aquadrop (mikami mika)] akahon (fate/stay night) [chinese]"}, {"img_url_number": "963170", "content_article_url": "https://hanime1.me/comic/51284", "content_article_name": "(c71) [shinpakusu teika (usami rui)] :ragtime (fate/stay night) [chinese]"}, {"img_url_number": "963148", "content_article_url": "https://hanime1.me/comic/51286", "content_article_name": "[last eden (amane mari)] destiny lover (fate/stay night) [chinese]"}, {"img_url_number": "961663", "content_article_url": "https://hanime1.me/comic/51376", "content_article_name": "(c89) [kamabokodokoro (nina)] yumemitsu nijimu (fate/stay night) [chinese] [ual汉化组]"}, {"img_url_number": "961276", "content_article_url": "https://hanime1.me/comic/51395", "content_article_name": "(c71) [last eden, gokuzyo syndrome (amane mari, sagami riku)] tohsaka jinja no hon. (fate/stay night) [chinese]"}, {"img_url_number": "960811", "content_article_url": "https://hanime1.me/comic/51421", "content_article_name": "(mimiket 10) [battle princess (bushidou tomoko, fni)] houseki hime to akai kishi (fate/stay night) [chinese]"}, {"img_url_number": "959335", "content_article_url": "https://hanime1.me/comic/51494", "content_article_name": "(c88) [ohkura bekkan (ohkura kazuya)] rin to shite... (fate/stay night) [chinese] [surely個人漢化]"}, {"img_url_number": "955844", "content_article_url": "https://hanime1.me/comic/51678", "content_article_name": "(cr36) [last eden (amane mari)] fall in destiny (fate/stay night) [chinese]"}, {"img_url_number": "947310", "content_article_url": "https://hanime1.me/comic/52166", "content_article_name": "(c66) [koubai gekka (kouno binshiho)] way to perdition (fate/stay night) [chinese]"}, {"img_url_number": "946368", "content_article_url": "https://hanime1.me/comic/52248", "content_article_name": "(c66) [hiland-studio (ueno naoya)] girl's capriccio 8 (fate/stay night) [chinese]"}, {"img_url_number": "945506", "content_article_url": "https://hanime1.me/comic/52303", "content_article_name": "(sc23) [tenjikuya (mochizuki nana)] another girl i (fate/stay night)"}, {"img_url_number": "943781", "content_article_url": "https://hanime1.me/comic/52429", "content_article_name": "(c71) [chicken chicken machine (tanabe satoru, inoue midori)] dakara yametoke tte itta desho!? (fate/stay night) [chinese]"}, {"img_url_number": "942716", "content_article_url": "https://hanime1.me/comic/52506", "content_article_name": "[yukirins (yuunyan)] gekkou no shita de odore! (fate/stay night) [chinese] [digital]"}, {"img_url_number": "942340", "content_article_url": "https://hanime1.me/comic/52530", "content_article_name": "(c65) [masulao maximum (kazekawa nagi)] are you ready? (fate/stay night) [chinese]"}, {"img_url_number": "941383", "content_article_url": "https://hanime1.me/comic/52573", "content_article_name": "(c71) [angel red (kawashima mitsuha)] promised land (fate/hollow ataraxia) [chinese]"}, {"img_url_number": "939610", "content_article_url": "https://hanime1.me/comic/52694", "content_article_name": "(spark10) [un-moto shoko (un-moto)] zettai ni eirei ga shoukan dekiru majutsu reisou | 絕對能召換英靈的魔術禮裝 (fate/grand order) [chinese]"}, {"img_url_number": "938140", "content_article_url": "https://hanime1.me/comic/52844", "content_article_name": "[ryu-seki-do (nagare hyo-go)] c-l (fate/stay night) [chinese]"}, {"img_url_number": "937193", "content_article_url": "https://hanime1.me/comic/52916", "content_article_name": "(tsukiyomi no utage) [tenjikuya (mochizuki nana)] rin no gogo tea (fate/stay night) [chinese]"}, {"img_url_number": "933857", "content_article_url": "https://hanime1.me/comic/53156", "content_article_name": "(c71) [girls...now (edoya pochi)] red zone (fate/stay night) [chinese]"}, {"img_url_number": "933598", "content_article_url": "https://hanime1.me/comic/53180", "content_article_name": "(mimiket 10) [red data book (amano ryuuki)] albireo (fate stay night) [chinese]"}, {"img_url_number": "932230", "content_article_url": "https://hanime1.me/comic/53263", "content_article_name": " seven cardinal sins  みりおんばんく [fate]"}, {"img_url_number": "931945", "content_article_url": "https://hanime1.me/comic/53282", "content_article_name": "(sc30) [ryu-seki-do (nagare hyo-go)] apostate (fate/hollow ataraxia) [chinese]"}, {"img_url_number": "931568", "content_article_url": "https://hanime1.me/comic/53309", "content_article_name": " seven cardinal sins  みりおんばんく [fate]"}, {"img_url_number": "931566", "content_article_url": "https://hanime1.me/comic/53310", "content_article_name": "[last eden (amane mari)] mitsugetsu (fate/stay night) [chinese]"}, {"img_url_number": "931269", "content_article_url": "https://hanime1.me/comic/53325", "content_article_name": "(c72) [gunburrel (ikura nagisa)] ikasete! archer (fate/stay night) [chinese]"}, {"img_url_number": "929475", "content_article_url": "https://hanime1.me/comic/53428", "content_article_name": "(c84) [abarenbow tengu (izumi yuujiro)] kotori zero 3 (fate/zero) [chinese] [baruto個人漢化]"}, {"img_url_number": "929442", "content_article_url": "https://hanime1.me/comic/53430", "content_article_name": "(comic1☆6) [abarenbow tengu (izumi yuujiro)] kotori 8 (fate/stay night) [chinese] [baruto個人漢化]"}, {"img_url_number": "928457", "content_article_url": "https://hanime1.me/comic/53499", "content_article_name": "(c69) [oukoku shineitai (satomi haruna)] nails (fate/stay night) [chinese]"}, {"img_url_number": "928412", "content_article_url": "https://hanime1.me/comic/53506", "content_article_name": "(c66) [tenjikuya (mochizuki nana)] another girl iii (fate/stay night) [chinese]"}, {"img_url_number": "928410", "content_article_url": "https://hanime1.me/comic/53507", "content_article_name": "(c70) [chicken chicken machine (tanabe satoru)] mahoshiki (fate/stay night) [chinese]"}, {"img_url_number": "926523", "content_article_url": "https://hanime1.me/comic/53628", "content_article_name": "(harucc19) [nonsense (em)] alternative gray (fate/stay night, fate/hollow ataraxia) [chinese]"}, {"img_url_number": "926243", "content_article_url": "https://hanime1.me/comic/53651", "content_article_name": "(c85) [unizo (unikura)] bitch queens wakuwaku poolside date (fate/stay night) [chinese]"}, {"img_url_number": "922383", "content_article_url": "https://hanime1.me/comic/53937", "content_article_name": "(sc31) [yuzuriha (aki, poso)] red and red (fate/stay night) [chinese]"}, {"img_url_number": "922251", "content_article_url": "https://hanime1.me/comic/53945", "content_article_name": " (cr35) [gold rush (suzuki address)] ~femme fatale~ (fate/stay night) [chinese] "}, {"img_url_number": "921519", "content_article_url": "https://hanime1.me/comic/53979", "content_article_name": "(c68) [knife edge (saki urara)] yoru ni saku mahou (fate/stay night) [chinese]"}, {"img_url_number": "921178", "content_article_url": "https://hanime1.me/comic/54001", "content_article_name": "(cr35) [tenjikuya (mochizuki nana)] another girl ii (fate/stay night) [chinese]"}, {"img_url_number": "920972", "content_article_url": "https://hanime1.me/comic/54004", "content_article_name": "(c66) [tenjikuya (mochizuki nana)] cute honey (fate/stay night) [chinese]"}, {"img_url_number": "919654", "content_article_url": "https://hanime1.me/comic/54065", "content_article_name": "(c66) [tekitou kaijuu, hikami oukoku (aoizumi rio, minazuki haruka)] seducer (fate/stay night) [chinese]"}, {"img_url_number": "919642", "content_article_url": "https://hanime1.me/comic/54067", "content_article_name": "(c65) [hanakaidou (hanakaidou yukio)] the plastic moon (fate/stay night) [chinese]"}, {"img_url_number": "919632", "content_article_url": "https://hanime1.me/comic/54068", "content_article_name": "(c87) [abarenbow tengu (izumi yuujiro)] kotori 11 (fate/stay night) [chinese] [个人汉化]"}, {"img_url_number": "915240", "content_article_url": "https://hanime1.me/comic/54342", "content_article_name": "(cr35) [knife edge (saki urara)] jigoku no kisetsu (fate/stay night) [chinese]"}, {"img_url_number": "915215", "content_article_url": "https://hanime1.me/comic/54345", "content_article_name": "[mangourt] imperialism (fate/stay night)"}, {"img_url_number": "915096", "content_article_url": "https://hanime1.me/comic/54354", "content_article_name": "(sc25) [cs205 (kineya emuko)] catharsis (fate/stay night) [chinese]"}, {"img_url_number": "915095", "content_article_url": "https://hanime1.me/comic/54355", "content_article_name": "(cr35) [hyoujooukoku (minaduki haruka)] relation (fate/stay night) [chinese]"}, {"img_url_number": "914958", "content_article_url": "https://hanime1.me/comic/54366", "content_article_name": "(c65) [renai mangaka (naruse hirofumi)] magic for you! (fate/stay night) [chinese]"}, {"img_url_number": "910862", "content_article_url": "https://hanime1.me/comic/54673", "content_article_name": "(harucc20) [monica (azuma)] miss perfect no xxx (fate/stay night) [chinese]"}, {"img_url_number": "909243", "content_article_url": "https://hanime1.me/comic/54755", "content_article_name": "(dai 4 tsugi root 4 to 5) [un-moto shoko (un-moto)] giji genkai toppa jikken houkokusho 01 (fate/grand order) [chinese] [incomplete]"}, {"img_url_number": "908567", "content_article_url": "https://hanime1.me/comic/54791", "content_article_name": "(c72) [virginal (uro-g)] unlimited aphrodisiac works (fate/stay night) [chinese]"}, {"img_url_number": "907675", "content_article_url": "https://hanime1.me/comic/54848", "content_article_name": "(c89) [jyouren kishidan (kiasa)] sakura neya (fate/stay night) [chinese] [脸肿汉化组]"}, {"img_url_number": "907654", "content_article_url": "https://hanime1.me/comic/54849", "content_article_name": "(c75) [yami ni ugomeku (dokurosan)] itanshinmon zettai shikei (fate/stay night) [chinese] [沒有漢化]"}, {"img_url_number": "907587", "content_article_url": "https://hanime1.me/comic/54852", "content_article_name": "(c89) [jyouren kishidan (kiasa)] sakura neya (fate/stay night) [chinese] [脸肿汉化组] [incomplete]"}, {"img_url_number": "907156", "content_article_url": "https://hanime1.me/comic/54875", "content_article_name": "[kyokuchokyoku (kyokucho)] rinjoku (fate/stay night) [chinese] [阿嘿颜大姐头汉化组] [digital]"}, {"img_url_number": "906829", "content_article_url": "https://hanime1.me/comic/54893", "content_article_name": "(c75) [yami ni ugomeku (dokurosan)] itanshinmon zettai shikei (fate/stay night) [chinese] [沒有漢化]"}, {"img_url_number": "905830", "content_article_url": "https://hanime1.me/comic/54970", "content_article_name": "(c69) [shinpakusu teika (usami rui)] shrouded in red (fate/stay night) [chinese]"}, {"img_url_number": "904555", "content_article_url": "https://hanime1.me/comic/55048", "content_article_name": "(super22) [altopia (alto)] watashi no archer | 我的archer (fate/stay night) [chinese] [冬木守護者漢化組]"}, {"img_url_number": "896576", "content_article_url": "https://hanime1.me/comic/55469", "content_article_name": "(c66) [nagasaki-inter (masutabe kokemaru, sou akiko)] love-craft (fate/stay night) [chinese] [冬木守護者漢化組]"}, {"img_url_number": "886784", "content_article_url": "https://hanime1.me/comic/56035", "content_article_name": "(c66) [hanzai tengoku (hasei agana)] access code primary (fate/stay night) [chinese] [冬木守護者漢化組]"}, {"img_url_number": "884470", "content_article_url": "https://hanime1.me/comic/56145", "content_article_name": "(spark10) [f.o.f (yukowa(kari))] aka to ao no akuma | 赤色与青色的恶魔 (fate/stay night) [chinese] [冬木守護者漢化組]"}, {"img_url_number": "871527", "content_article_url": "https://hanime1.me/comic/56680", "content_article_name": "(ff25) [o-penguin (ramen-penguin)] mousou, bousou, tairyuuken | delusions, frenzy, tropospheric (fate/hollow ataraxia) [chinese]"}, {"img_url_number": "870477", "content_article_url": "https://hanime1.me/comic/56722", "content_article_name": "(c65) [iiwake-gaisya (shigemiya kyouhei)] magician's red (fate/stay night) [chinese] [wl00314824個人漢化]"}, {"img_url_number": "865405", "content_article_url": "https://hanime1.me/comic/56923", "content_article_name": "(c72) [studio eko (suzunari ichigo)] himitsu nikki 1 ~toosaka-san no himitsu diary~ (fate/stay night) [chinese] [wl00314824個人漢化]"}, {"img_url_number": "855105", "content_article_url": "https://hanime1.me/comic/57431", "content_article_name": "(c88) [o-penguin (ramen-penguin)] gyaku maryoku kyoukyuu - mana reverse transfer (fate/stay night) [chinese]"}, {"img_url_number": "850367", "content_article_url": "https://hanime1.me/comic/57664", "content_article_name": "(c88) [null mayu (chimosaku)] taihai no susume | 頹廢的勸誘 (fate/stay night) [chinese] {g&南音的暗黑女子力研究}"}, {"img_url_number": "850213", "content_article_url": "https://hanime1.me/comic/57676", "content_article_name": "[nonsense (em)] one/stay night (fate/stay night) [chinese] [wl00314824個人漢化]"}, {"img_url_number": "848844", "content_article_url": "https://hanime1.me/comic/57750", "content_article_name": "(c88) [z.a.p. (zucchini)] shirou-kun harem!! (fate/stay night) [chinese] [脸肿汉化组]"}, {"img_url_number": "848086", "content_article_url": "https://hanime1.me/comic/57788", "content_article_name": "(c88) [pno group (hase yuu, hikawa yuuki)] carni☆phan tic factory 8 (fate/kaleid liner prisma illya) [chinese] [脸肿汉化组]"}, {"img_url_number": "847983", "content_article_url": "https://hanime1.me/comic/57798", "content_article_name": "(comic1☆9) [mamagotoya (maino umi)] emiya-ke no hanayome (fate/stay night) [chinese] [wl00314824個人漢化]"}, {"img_url_number": "847528", "content_article_url": "https://hanime1.me/comic/57818", "content_article_name": "[aquadrop (mikami mika)] yappari yumi rin ga suki! (fate/stay night) [chinese] [wl00314824個人漢化] [digital]"}, {"img_url_number": "847206", "content_article_url": "https://hanime1.me/comic/57830", "content_article_name": "(c80) [mumu@ (shirokai mua)] good-chu!×2 (fate/stay night) [chinese] [wl00314824個人漢化]"}, {"img_url_number": "845583", "content_article_url": "https://hanime1.me/comic/57924", "content_article_name": "(c88) [rubbish selecting squad (namonashi)] re22 (fate/stay night) [chinese]  [无毒汉化组]"}, {"img_url_number": "828912", "content_article_url": "https://hanime1.me/comic/58644", "content_article_name": "(c71) [bubblemint (nitou yuusa)] caramel×milk (fate/stay night)"}, {"img_url_number": "826196", "content_article_url": "https://hanime1.me/comic/58770", "content_article_name": "[hanakairou] slight fever (fate/stay night) [chinese] [wl00314824個人漢化] [digital]"}, {"img_url_number": "825193", "content_article_url": "https://hanime1.me/comic/58825", "content_article_name": "[studio big-x (arino hiroshi)] mousou theater 19 (fate/stay night) [chinese] [wl00314824個人漢化] [digital] [incomplete]"}, {"img_url_number": "825190", "content_article_url": "https://hanime1.me/comic/58826", "content_article_name": "(comic1☆9) [un-moto shoko (un-moto)] berry very belly (fate/stay night) [chinese] [wl00314824個人漢化]"}, {"img_url_number": "825015", "content_article_url": "https://hanime1.me/comic/58833", "content_article_name": " (mimiket 10) [happy water (kizaki yuuri)] -true night- (fate/stay night) [chinese] [wl00314824個人漢化] "}, {"img_url_number": "824988", "content_article_url": "https://hanime1.me/comic/58837", "content_article_name": "(sc35) [studioeko (suzunari ichigo)] guren ni (fate/stay night) [chinese] [wl00314824個人漢化]"}, {"img_url_number": "824984", "content_article_url": "https://hanime1.me/comic/58841", "content_article_name": "(c71) [studioeko (suzunari ichigo)] guren ichi (fate/stay night) [chinese] [wl00314824個人漢化]"}, {"img_url_number": "824974", "content_article_url": "https://hanime1.me/comic/58842", "content_article_name": "(c66) [happy water (kizaki yuuri)] restraint. (fate/stay night) [chinese] [wl00314824個人漢化]"}, {"img_url_number": "824892", "content_article_url": "https://hanime1.me/comic/58847", "content_article_name": "(c67) [studio himawari (himukai kyousuke)] berry berry (fate/stay night) [chinese] [wl00314824個人漢化]"}, {"img_url_number": "824890", "content_article_url": "https://hanime1.me/comic/58848", "content_article_name": "(c74) [einfach (tomoya)] a midsummer night's dream (fate/stay night) [chinese] [wl00314824個人漢化] [incomplete]"}, {"img_url_number": "824887", "content_article_url": "https://hanime1.me/comic/58849", "content_article_name": "(sc25) [fantasy wind (minazuki satoshi, shinano yura)] permeate (fate/stay night, tsukihime) [chinese] [wl00314824個人漢化]"}, {"img_url_number": "823632", "content_article_url": "https://hanime1.me/comic/58908", "content_article_name": "(c66) [badon (kida, kine)] candy (fate/stay night) [chinese] [wl00314824個人漢化]"}, {"img_url_number": "823629", "content_article_url": "https://hanime1.me/comic/58909", "content_article_name": "(c66) [badon (kida, kine)] double spiral (fate/stay night) [chinese] [wl00314824個人漢化]"}, {"img_url_number": "823207", "content_article_url": "https://hanime1.me/comic/58932", "content_article_name": "(c67) [kabayakiya (unagimaru)] red side (fate/stay night) [chinese] [wl00314824個人漢化]"}, {"img_url_number": "823205", "content_article_url": "https://hanime1.me/comic/58933", "content_article_name": "(ou no utsuwa 11) [mamagotoya (maino umi)] virgin killer (fate/stay night) [chinese] [wl00314824個人漢化]"}, {"img_url_number": "822880", "content_article_url": "https://hanime1.me/comic/58948", "content_article_name": "(c72) [c.a.t (morisaki kurumi)] red/ii (fate/stay night) [chinese] [wl00314824個人漢化]"}, {"img_url_number": "822870", "content_article_url": "https://hanime1.me/comic/58950", "content_article_name": "(comicomi10) [gunburrel (ikura nagisa)] silhouette x (fate/stay night) [chinese] [wl00314824個人漢化]"}, {"img_url_number": "822869", "content_article_url": "https://hanime1.me/comic/58951", "content_article_name": "(c86) [unizo (unikura)] ichaicha maryoku kyoukyuu (fate/stay night) [chinese] [wl00314824個人漢化] [incomplete]"}, {"img_url_number": "819076", "content_article_url": "https://hanime1.me/comic/59150", "content_article_name": "(ccosaka100) [aiviera (mihara nori)] kono te o nobaseba (fate/stay night) [chinese] [wl00314824個人漢化]"}, {"img_url_number": "819075", "content_article_url": "https://hanime1.me/comic/59151", "content_article_name": "(comicomi9) [udon-ya (kizuki aruchu, zan)] nekomimi hadaka epurin (fate/stay night) [chinese] [wl00314824個人漢化]"}, {"img_url_number": "819073", "content_article_url": "https://hanime1.me/comic/59152", "content_article_name": "(c66) [neko kinryouku (nekoneko)] master wa child (fate/stay night) [chinese] [wl00314824個人漢化]"}, {"img_url_number": "817558", "content_article_url": "https://hanime1.me/comic/59218", "content_article_name": "(comic1☆9) [cior (ken-1)] tosaka rin ga berserker ni okasareru hon (fate/stay night) [chinese] [ce家族社]"}, {"img_url_number": "816497", "content_article_url": "https://hanime1.me/comic/59248", "content_article_name": "(super24) [f.o.f (yukowa(kari))] oubou to onjou no shujuu ai (fate/stay night) [chinese] [脸肿汉化组]"}, {"img_url_number": "813824", "content_article_url": "https://hanime1.me/comic/59392", "content_article_name": "(c86) [rubbish selecting squad (namonashi)] re20 (fate/kaleid liner prisma illya) [chinese] [落莲汉化组]"}, {"img_url_number": "809488", "content_article_url": "https://hanime1.me/comic/59593", "content_article_name": "(c70) [c.a.t (morisaki kurumi)] red (fate/stay night) [chinese] [wl00314824個人漢化]"}, {"img_url_number": "809487", "content_article_url": "https://hanime1.me/comic/59594", "content_article_name": "(c73) [taiyaki yaketa (ikeda shuuko)] ura☆chibicchai tte koto wa (fate/stay night) [chinese] [wl00314824個人漢化]"}, {"img_url_number": "809227", "content_article_url": "https://hanime1.me/comic/59601", "content_article_name": "(harucc20) [aiviera (mihara nori)] barecha ikenai (fate/stay night) [chinese] [wl00314824個人漢化]"}, {"img_url_number": "808146", "content_article_url": "https://hanime1.me/comic/59651", "content_article_name": "(sc35) [girls... now (edoya pochi)] red zone 3 (fate/stay night) [chinese] [wl00314824個人漢化]"}, {"img_url_number": "803706", "content_article_url": "https://hanime1.me/comic/59867", "content_article_name": "(cr35) [badon (kida, kine)] blue blood (fate/stay night) [chinese] [中文漢化]"}, {"img_url_number": "792458", "content_article_url": "https://hanime1.me/comic/60336", "content_article_name": "(c87) [million☆drops (tanimura marika)] ore no master ga konnani kawaii hazu ga nai (fate/stay night) [chinese] [脸肿汉化组]"}, {"img_url_number": "781673", "content_article_url": "https://hanime1.me/comic/60837", "content_article_name": "(c87) [high thrust (inomaru)] rinkan mahou (fate/stay night) [chinese] [matsuri个人汉化]"}]